[
  {
    "endTerm": "October 21, 1886",
    "name": "George Murdoch",
    "beginTerm": "December 4, 1884",
    "era": ""
  },
  {
    "endTerm": "January 16, 1888",
    "name": "George Clift King",
    "beginTerm": "November 4, 1886",
    "era": ""
  },
  {
    "endTerm": "January 21, 1889",
    "name": "Arthur Edwin Shelton",
    "beginTerm": "January 16, 1888",
    "era": ""
  },
  {
    "endTerm": "January 20, 1890",
    "name": "Daniel Webster Marsh",
    "beginTerm": "January 21, 1889",
    "era": ""
  },
  {
    "endTerm": "January 19, 1891",
    "name": "James Delamere Lafferty",
    "beginTerm": "January 20, 1890",
    "era": ""
  },
  {
    "endTerm": "January 18, 1892",
    "name": "James Reilly",
    "beginTerm": "January 19, 1891",
    "era": ""
  },
  {
    "endTerm": "January 2, 1894",
    "name": "Alexander Lucas",
    "beginTerm": "January 18, 1892",
    "era": ""
  },
  {
    "endTerm": "January 6, 1896",
    "name": "Wesley Fletcher Orr",
    "beginTerm": "January 16, 1894",
    "era": ""
  },
  {
    "endTerm": "January 4, 1897",
    "name": "Alexander McBride",
    "beginTerm": "January 6, 1896",
    "era": ""
  },
  {
    "endTerm": "January 3, 1898",
    "name": "Wesley Fletcher Orr (2nd time)",
    "beginTerm": "January 4, 1897",
    "era": ""
  },
  {
    "endTerm": "January 3, 1899",
    "name": "Arthur Leslie Cameron",
    "beginTerm": "January 3, 1898",
    "era": ""
  },
  {
    "endTerm": "January 2, 1900",
    "name": "James Reilly (2nd time)",
    "beginTerm": "January 3, 1899",
    "era": ""
  },
  {
    "endTerm": "January 7, 1901",
    "name": "William Henry Cushing",
    "beginTerm": "January 2, 1900",
    "era": ""
  },
  {
    "endTerm": "January 6, 1902",
    "name": "James Stuart Mackie",
    "beginTerm": "January 7, 1901",
    "era": ""
  },
  {
    "endTerm": "January 5, 1904",
    "name": "Thomas Underwood",
    "beginTerm": "January 6, 1902",
    "era": ""
  },
  {
    "endTerm": "January 2, 1905",
    "name": "Silas Alexander Ramsay",
    "beginTerm": "January 5, 1904",
    "era": ""
  },
  {
    "endTerm": "January 14, 1907",
    "name": "John Emerson",
    "beginTerm": "January 2, 1905",
    "era": ""
  },
  {
    "endTerm": "January 2, 1909",
    "name": "Arthur Leslie Cameron (2nd time)",
    "beginTerm": "January 14, 1907",
    "era": ""
  },
  {
    "endTerm": "January 2, 1911",
    "name": "Reuben Rupert Jamieson",
    "beginTerm": "January 2, 1909",
    "era": ""
  },
  {
    "endTerm": "January 2, 1913",
    "name": "John William Mitchell",
    "beginTerm": "January 2, 1911",
    "era": ""
  },
  {
    "endTerm": "January 2, 1915",
    "name": "Herbert Arthur Sinnott",
    "beginTerm": "January 2, 1913",
    "era": ""
  },
  {
    "endTerm": "January 2, 1919",
    "name": "Michael Copps Costello",
    "beginTerm": "January 2, 1915",
    "era": ""
  },
  {
    "endTerm": "January 3, 1921",
    "name": "Robert Colin Marshall",
    "beginTerm": "January 2, 1919",
    "era": ""
  },
  {
    "endTerm": "January 2, 1923",
    "name": "Samuel Hunter Adams",
    "beginTerm": "January 3, 1921",
    "era": ""
  },
  {
    "endTerm": "December 31, 1926",
    "name": "George Harry Webster",
    "beginTerm": "January 2, 1923",
    "era": ""
  },
  {
    "endTerm": "December 31, 1929",
    "name": "Frederick Ernest Osborne",
    "beginTerm": "January 3, 1927",
    "era": ""
  },
  {
    "endTerm": "December 31, 1945",
    "name": "Andrew Davison",
    "beginTerm": "January 1, 1930",
    "era": ""
  },
  {
    "endTerm": "December 31, 1949",
    "name": "James Cameron Watson",
    "beginTerm": "January 1, 1946",
    "era": ""
  },
  {
    "endTerm": "October 19, 1959",
    "name": "Donald Hugh Mackay",
    "beginTerm": "January 1, 1950",
    "era": ""
  },
  {
    "endTerm": "June 30, 1963",
    "name": "Harry William Hays",
    "beginTerm": "October 19, 1959",
    "era": ""
  },
  {
    "endTerm": "October 18, 1965",
    "name": "John Walter Grant MacEwan",
    "beginTerm": "July 4, 1963",
    "era": ""
  },
  {
    "endTerm": "October 22, 1969",
    "name": "John Clifford Leslie",
    "beginTerm": "October 18, 1965",
    "era": ""
  },
  {
    "endTerm": "October 31, 1977",
    "name": "James Rodney Winter Sykes",
    "beginTerm": "October 22, 1969",
    "era": ""
  },
  {
    "endTerm": "October 27, 1980",
    "name": "Ross Patterson Alger",
    "beginTerm": "October 31, 1977",
    "era": ""
  },
  {
    "endTerm": "March 21, 1989",
    "name": "Ralph Phillip Klein",
    "beginTerm": "October 27, 1980",
    "era": ""
  },
  {
    "endTerm": "October 23, 1989",
    "name": "Donald Adam Hartman",
    "beginTerm": "March 21, 1989",
    "era": ""
  },
  {
    "endTerm": "October 22, 2001",
    "name": "Alfred Herman Duerr",
    "beginTerm": "October 23, 1989",
    "era": ""
  },
  {
    "endTerm": "October 25, 2010",
    "name": "David Thomas Bronconnier",
    "beginTerm": "October 22, 2001",
    "era": ""
  },
  {
    "endTerm": "Present",
    "name": "Naheed Kurban Nenshi",
    "beginTerm": "October 25, 2010",
    "era": ""
  }
]
